{
    "iit-bhu-varanasi": {
        "overview": {
            "Institute Name": "Indian Institute of Technology (Banaras Hindu University), Varanasi",
            "Also Known As": "IIT (BHU)",
            "Institute Type": "Government",
            "Established": "1919",
            "Location": "Varanasi, Uttar Pradesh",
            "address": "Indian Institute of Technology (Banaras Hindu University), Varanasi, Uttar Pradesh – 221005"
        },
        "mode_of_admission": {
            "mode_of_admission": "Candidates must qualify the JEE (Main) exam and then appear for the JEE (Advanced) exam."
        },
        "fee_structure": {
            "Caution Money (One-Time, Refundable)": "₹9,000",
            "One-Time Fees": "₹5,750",
            "Tuition Fee (per Semester)": "₹1,00,000",
            "Other Fees (per Semester)": "₹6,350",
            "Mess Advance (per Semester)": "₹15,000",
            "Annual Fees": "₹365",
            "Total": "₹1,36,465"
        },
        "fee_waiver": {
            "point 1": "100% Tuition Fee waiver for SC/ST/PwD students.",
            "point 2": "100% Tuition Fee remission for Most Economically Backward students with family income less than ₹1 lakh per annum.",
            "point 3": "2/3rd Tuition Fee remission for Other Economically Backward students with family income between ₹1 lakh to ₹5 lakh per annum."
        },
        "photos":{
            "logo":"",
            "college-pic":""
        }
    }
}